imad213tools/__init__.py
imad213tools/main.py
imad213tools-213.dist-info/METADATA
imad213tools-213.dist-info/WHEEL
imad213tools-213.dist-info/entry_points.txt
imad213tools-213.dist-info/top_level.txt
imad213tools-213.dist-info/RECORD
