Metadata-Version: 2.4
Name: imad213tools
Version: 213
Summary: The imad213 followers tool is back under a new name: imad213tools — faster, smarter, and ready for action.
Author: IMAD 213
Author-email: madmadimado59@gmail.com
Classifier: Programming Language :: Python :: 3
Classifier: License :: OSI Approved :: MIT License
Classifier: Operating System :: OS Independent
Classifier: Topic :: Security :: Cryptography
Requires-Python: >=3.6
Requires-Dist: requests
Requires-Dist: bs4
Requires-Dist: pycryptodome>=3.19.0
Requires-Dist: pyfiglet>=0.8.post1
Requires-Dist: psutil
Dynamic: author
Dynamic: author-email
Dynamic: classifier
Dynamic: description
Dynamic: description-content-type
Dynamic: requires-dist
Dynamic: requires-python
Dynamic: summary
